README.md
setup.py
earthquake_check.egg-info/PKG-INFO
earthquake_check.egg-info/SOURCES.txt
earthquake_check.egg-info/dependency_links.txt
earthquake_check.egg-info/entry_points.txt
earthquake_check.egg-info/requires.txt
earthquake_check.egg-info/top_level.txt
equake/__init__.py
equake/api.py
equake/models.py
equake/service.py