Metadata-Version: 2.1
Name: earthquake-check
Version: 0.1.0
Summary: A package for checking earthquake information in Taiwan.
Home-page: https://github.com/ChickenBenny/equake-check
Author: ChickenBenny
Author-email: zxc123benny14159@gmail.com
License: UNKNOWN
Platform: UNKNOWN
Classifier: Programming Language :: Python :: 3
Classifier: Programming Language :: Python :: 3.6
Classifier: Programming Language :: Python :: 3.7
Classifier: Programming Language :: Python :: 3.8
Classifier: Programming Language :: Python :: 3.9
Classifier: License :: OSI Approved :: MIT License
Classifier: Operating System :: OS Independent
Requires-Python: >=3.6
